pulumiverse_talos/__init__.py
pulumiverse_talos/_utilities.py
pulumiverse_talos/provider.py
pulumiverse_talos/pulumi-plugin.json
pulumiverse_talos/py.typed
pulumiverse_talos/client/__init__.py
pulumiverse_talos/client/_inputs.py
pulumiverse_talos/client/get_configuration.py
pulumiverse_talos/client/outputs.py
pulumiverse_talos/cluster/__init__.py
pulumiverse_talos/cluster/_inputs.py
pulumiverse_talos/cluster/get_health.py
pulumiverse_talos/cluster/get_kubeconfig.py
pulumiverse_talos/cluster/kubeconfig.py
pulumiverse_talos/cluster/outputs.py
pulumiverse_talos/config/__init__.py
pulumiverse_talos/config/__init__.pyi
pulumiverse_talos/config/vars.py
pulumiverse_talos/imagefactory/__init__.py
pulumiverse_talos/imagefactory/_inputs.py
pulumiverse_talos/imagefactory/get_extensions_versions.py
pulumiverse_talos/imagefactory/get_overlays_versions.py
pulumiverse_talos/imagefactory/get_urls.py
pulumiverse_talos/imagefactory/get_versions.py
pulumiverse_talos/imagefactory/outputs.py
pulumiverse_talos/imagefactory/schematic.py
pulumiverse_talos/machine/__init__.py
pulumiverse_talos/machine/_inputs.py
pulumiverse_talos/machine/bootstrap.py
pulumiverse_talos/machine/configuration_apply.py
pulumiverse_talos/machine/get_configuration.py
pulumiverse_talos/machine/get_disks.py
pulumiverse_talos/machine/outputs.py
pulumiverse_talos/machine/secrets.py
pulumiverse_talos-0.7.1.dist-info/METADATA
pulumiverse_talos-0.7.1.dist-info/WHEEL
pulumiverse_talos-0.7.1.dist-info/top_level.txt
pulumiverse_talos-0.7.1.dist-info/RECORD
