Metadata-Version: 2.4
Name: pulumiverse_talos
Version: 0.7.1
Summary: A Pulumi package for creating and managing Talos Linux machines and clusters.
License: MPL-2.0
Project-URL: Homepage, https://www.talos.dev
Project-URL: Repository, https://github.com/pulumiverse/pulumi-talos
Keywords: pulumi,talos,category/infrastructure
Requires-Python: >=3.9
Requires-Dist: parver>=0.2.1
Requires-Dist: pulumi<4.0.0,>=3.0.0
Requires-Dist: semver>=2.8.1
Requires-Dist: typing-extensions<5,>=4.11; python_version < "3.11"
